geonlplify/__init__.py
geonlplify/geonlplify.py
test/__init__.py
test/manipulate_package.py
geonlplify-0.3.1.dist-info/LICENSE
geonlplify-0.3.1.dist-info/METADATA
geonlplify-0.3.1.dist-info/WHEEL
geonlplify-0.3.1.dist-info/top_level.txt
geonlplify-0.3.1.dist-info/RECORD
