Metadata-Version: 2.1
Name: geonlplify
Version: 0.3.1
Summary: GeoNLPlify aims to make variations of an input sentence working on spatial information contained in words
Home-page: https://github.com/remydecoupes/GeoNLPlify
Author: Rémy Decoupes
Author-email: 
License: UNKNOWN
Platform: UNKNOWN
Classifier: Programming Language :: Python
Classifier: Programming Language :: Python :: 3
Classifier: Programming Language :: Python :: 3.10
License-File: LICENSE
Requires-Dist: pandas
Requires-Dist: requests
Requires-Dist: spacy (<=2.3.999,>=2.3.0)
Requires-Dist: importlib-metadata (<=3.999,>=3.7.0)
Requires-Dist: typing-extensions (<=3.999,>=3.7.4)
Requires-Dist: transformers (<=4.15.999,>=3.4.0)
